cellvgae/__init__.py
cellvgae/__main__.py
cellvgae/models/CellVGAE.py
cellvgae/models/CellVGAE_Encoder.py
cellvgae/models/__init__.py
cellvgae/models/mmd.py
cellvgae/utils/__init__.py
cellvgae/utils/attn_graph.py
cellvgae/utils/top_genes.py
cellvgae-0.0.1b4.dist-info/LICENSE
cellvgae-0.0.1b4.dist-info/METADATA
cellvgae-0.0.1b4.dist-info/WHEEL
cellvgae-0.0.1b4.dist-info/top_level.txt
cellvgae-0.0.1b4.dist-info/RECORD
