Metadata-Version: 2.1
Name: cellvgae
Version: 0.0.1b4
Summary: CellVGAE uses the connectivity between cells (such as k-nearest neighbour graphs) with gene expression values as node features to learn high-quality cell representations in a lower-dimensional space
Home-page: https://github.com/davidbuterez/CellVGAE
Author: David Buterez
Author-email: david.buterez@gmail.com
License: MIT
Keywords: scrnaseq,graph,gnn,dimensionality,reduction,neural
Platform: UNKNOWN
Classifier: Development Status :: 3 - Alpha
Classifier: Intended Audience :: Science/Research
Classifier: License :: OSI Approved :: MIT License
Classifier: Programming Language :: Python :: 3
License-File: LICENSE
Requires-Dist: torch (>=1.6.0)
Requires-Dist: umap-learn (>=0.5.1)
Requires-Dist: hdbscan (>=0.8.27)
Requires-Dist: seaborn (>=0.11.1)
Requires-Dist: matplotlib (>=3.3.4)
Requires-Dist: scanpy (>=1.7.2)
Requires-Dist: anndata (>=0.7.5)
Requires-Dist: tqdm (>=4.61.2)
Requires-Dist: termcolor (>=1.1.0)
Requires-Dist: numpy (>=1.19.5)
Requires-Dist: pandas (>=1.2.4)
Requires-Dist: torch-geometric (>=1.7.0)
Requires-Dist: scikit-learn (>=0.24.2)
Requires-Dist: torch-sparse (>=0.6.12)
Requires-Dist: torch-scatter (>=2.0.8)
